cookiecutter_example/__init__.py
cookiecutter_example/foo.py
cookiecutter_example-1.0.3.dist-info/METADATA
cookiecutter_example-1.0.3.dist-info/WHEEL
cookiecutter_example-1.0.3.dist-info/licenses/LICENSE
cookiecutter_example-1.0.3.dist-info/RECORD
