Metadata-Version: 2.4
Name: cookiecutter-example
Version: 1.0.3
Summary: This is a template repository for Python projects that use uv for their dependency management.
Project-URL: Homepage, https://reece.github.io/cookiecutter-example/
Project-URL: Repository, https://github.com/reece/cookiecutter-example
Project-URL: Documentation, https://reece.github.io/cookiecutter-example/
Author-email: Reece Hart <reecehart@gmail.com>
License-File: LICENSE
Keywords: python
Classifier: Intended Audience :: Developers
Classifier: Programming Language :: Python
Classifier: Programming Language :: Python :: 3
Classifier: Programming Language :: Python :: 3.9
Classifier: Programming Language :: Python :: 3.10
Classifier: Programming Language :: Python :: 3.11
Classifier: Programming Language :: Python :: 3.12
Classifier: Programming Language :: Python :: 3.13
Classifier: Topic :: Software Development :: Libraries :: Python Modules
Requires-Python: <4.0,>=3.9
